{
    "data": {
        "Rows": [
            {
                "Columns": [
                    {
                        "Index": 0,
                        "Scale": 2,
                        "SecondaryValue": null,
                        "IsDominatingDirection": false,
                        "IsValid": true,
                        "IsAdditionalData": false,
                        "Behavior": 0,
                        "Name": "DK1",
                        "Value": "1 715,78",
                        "GroupHeader": "",
                        "DisplayNegativeValueInBlue": false,
                        "CombinedName": "DK1",
                        "DateTimeForData": "0001-01-01T00:00:00",
                        "DisplayName": "1 715,78_False",
                        "DisplayNameOrDominatingDirection": "1 715,78",
                        "IsOfficial": false,
                        "UseDashDisplayStyle": false
                    },
                    {
                        "Index": 1,
                        "Scale": 2,
                        "SecondaryValue": null,
                        "IsDominatingDirection": false,
                        "IsValid": true,
                        "IsAdditionalData": false,
                        "Behavior": 0,
                        "Name": "DK2",
                        "Value": "1 715,78",
                        "GroupHeader": "",
                        "DisplayNegativeValueInBlue": false,
                        "CombinedName": "DK2",
                        "DateTimeForData": "0001-01-01T00:00:00",
                        "DisplayName": "1 715,78_False",
                        "DisplayNameOrDominatingDirection": "1 715,78",
                        "IsOfficial": false,
                        "UseDashDisplayStyle": false
                    }
                ],
                "Name": "00&nbsp;-&nbsp;01",
                "StartTime": "2022-12-04T00:00:00",
                "EndTime": "2022-12-04T01:00:00",
                "DateTimeForData": "0001-01-01T00:00:00",
                "DayNumber": 0,
                "StartTimeDate": "0001-01-01T00:00:00",
                "IsExtraRow": false,
                "IsNtcRow": false,
                "EmptyValue": "",
                "Parent": null
            },
            {
                "Columns": [
                    {
                        "Index": 0,
                        "Scale": 2,
                        "SecondaryValue": null,
                        "IsDominatingDirection": false,
                        "IsValid": true,
                        "IsAdditionalData": false,
                        "Behavior": 0,
                        "Name": "DK1",
                        "Value": "1 635,60",
                        "GroupHeader": "",
                        "DisplayNegativeValueInBlue": false,
                        "CombinedName": "DK1",
                        "DateTimeForData": "0001-01-01T00:00:00",
                        "DisplayName": "1 635,60_False",
                        "DisplayNameOrDominatingDirection": "1 635,60",
                        "IsOfficial": false,
                        "UseDashDisplayStyle": false
                    },
                    {
                        "Index": 1,
                        "Scale": 2,
                        "SecondaryValue": null,
                        "IsDominatingDirection": false,
                        "IsValid": true,
                        "IsAdditionalData": false,
                        "Behavior": 0,
                        "Name": "DK2",
                        "Value": "1 635,60",
                        "GroupHeader": "",
                        "DisplayNegativeValueInBlue": false,
                        "CombinedName": "DK2",
                        "DateTimeForData": "0001-01-01T00:00:00",
                        "DisplayName": "1 635,60_False",
                        "DisplayNameOrDominatingDirection": "1 635,60",
                        "IsOfficial": false,
                        "UseDashDisplayStyle": false
                    }
                ],
                "Name": "01&nbsp;-&nbsp;02",
                "StartTime": "2022-12-04T01:00:00",
                "EndTime": "2022-12-04T02:00:00",
                "DateTimeForData": "0001-01-01T00:00:00",
                "DayNumber": 0,
                "StartTimeDate": "0001-01-01T00:00:00",
                "IsExtraRow": false,
                "IsNtcRow": false,
                "EmptyValue": "",
                "Parent": null
            },
            {
                "Columns": [
                    {
                        "Index": 0,
                        "Scale": 2,
                        "SecondaryValue": null,
                        "IsDominatingDirection": false,
                        "IsValid": true,
                        "IsAdditionalData": false,
                        "Behavior": 0,
                        "Name": "DK1",
                        "Value": "1 719,42",
                        "GroupHeader": "",
                        "DisplayNegativeValueInBlue": false,
                        "CombinedName": "DK1",
                        "DateTimeForData": "0001-01-01T00:00:00",
                        "DisplayName": "1 719,42_False",
                        "DisplayNameOrDominatingDirection": "1 719,42",
                        "IsOfficial": false,
                        "UseDashDisplayStyle": false
                    },
                    {
                        "Index": 1,
                        "Scale": 2,
                        "SecondaryValue": null,
                        "IsDominatingDirection": false,
                        "IsValid": true,
                        "IsAdditionalData": false,
                        "Behavior": 0,
                        "Name": "DK2",
                        "Value": "1 719,42",
                        "GroupHeader": "",
                        "DisplayNegativeValueInBlue": false,
                        "CombinedName": "DK2",
                        "DateTimeForData": "0001-01-01T00:00:00",
                        "DisplayName": "1 719,42_False",
                        "DisplayNameOrDominatingDirection": "1 719,42",
                        "IsOfficial": false,
                        "UseDashDisplayStyle": false
                    }
                ],
                "Name": "02&nbsp;-&nbsp;03",
                "StartTime": "2022-12-04T02:00:00",
                "EndTime": "2022-12-04T03:00:00",
                "DateTimeForData": "0001-01-01T00:00:00",
                "DayNumber": 0,
                "StartTimeDate": "0001-01-01T00:00:00",
                "IsExtraRow": false,
                "IsNtcRow": false,
                "EmptyValue": "",
                "Parent": null
            },
            {
                "Columns": [
                    {
                        "Index": 0,
                        "Scale": 2,
                        "SecondaryValue": null,
                        "IsDominatingDirection": false,
                        "IsValid": true,
                        "IsAdditionalData": false,
                        "Behavior": 0,
                        "Name": "DK1",
                        "Value": "1 552,97",
                        "GroupHeader": "",
                        "DisplayNegativeValueInBlue": false,
                        "CombinedName": "DK1",
                        "DateTimeForData": "0001-01-01T00:00:00",
                        "DisplayName": "1 552,97_False",
                        "DisplayNameOrDominatingDirection": "1 552,97",
                        "IsOfficial": false,
                        "UseDashDisplayStyle": false
                    },
                    {
                        "Index": 1,
                        "Scale": 2,
                        "SecondaryValue": null,
                        "IsDominatingDirection": false,
                        "IsValid": true,
                        "IsAdditionalData": false,
                        "Behavior": 0,
                        "Name": "DK2",
                        "Value": "1 566,96",
                        "GroupHeader": "",
                        "DisplayNegativeValueInBlue": false,
                        "CombinedName": "DK2",
                        "DateTimeForData": "0001-01-01T00:00:00",
                        "DisplayName": "1 566,96_False",
                        "DisplayNameOrDominatingDirection": "1 566,96",
                        "IsOfficial": false,
                        "UseDashDisplayStyle": false
                    }
                ],
                "Name": "03&nbsp;-&nbsp;04",
                "StartTime": "2022-12-04T03:00:00",
                "EndTime": "2022-12-04T04:00:00",
                "DateTimeForData": "0001-01-01T00:00:00",
                "DayNumber": 0,
                "StartTimeDate": "0001-01-01T00:00:00",
                "IsExtraRow": false,
                "IsNtcRow": false,
                "EmptyValue": "",
                "Parent": null
            },
            {
                "Columns": [
                    {
                        "Index": 0,
                        "Scale": 2,
                        "SecondaryValue": null,
                        "IsDominatingDirection": false,
                        "IsValid": true,
                        "IsAdditionalData": false,
                        "Behavior": 0,
                        "Name": "DK1",
                        "Value": "1 550,82",
                        "GroupHeader": "",
                        "DisplayNegativeValueInBlue": false,
                        "CombinedName": "DK1",
                        "DateTimeForData": "0001-01-01T00:00:00",
                        "DisplayName": "1 550,82_False",
                        "DisplayNameOrDominatingDirection": "1 550,82",
                        "IsOfficial": false,
                        "UseDashDisplayStyle": false
                    },
                    {
                        "Index": 1,
                        "Scale": 2,
                        "SecondaryValue": null,
                        "IsDominatingDirection": false,
                        "IsValid": true,
                        "IsAdditionalData": false,
                        "Behavior": 0,
                        "Name": "DK2",
                        "Value": "1 557,44",
                        "GroupHeader": "",
                        "DisplayNegativeValueInBlue": false,
                        "CombinedName": "DK2",
                        "DateTimeForData": "0001-01-01T00:00:00",
                        "DisplayName": "1 557,44_False",
                        "DisplayNameOrDominatingDirection": "1 557,44",
                        "IsOfficial": false,
                        "UseDashDisplayStyle": false
                    }
                ],
                "Name": "04&nbsp;-&nbsp;05",
                "StartTime": "2022-12-04T04:00:00",
                "EndTime": "2022-12-04T05:00:00",
                "DateTimeForData": "0001-01-01T00:00:00",
                "DayNumber": 0,
                "StartTimeDate": "0001-01-01T00:00:00",
                "IsExtraRow": false,
                "IsNtcRow": false,
                "EmptyValue": "",
                "Parent": null
            },
            {
                "Columns": [
                    {
                        "Index": 0,
                        "Scale": 2,
                        "SecondaryValue": null,
                        "IsDominatingDirection": false,
                        "IsValid": true,
                        "IsAdditionalData": false,
                        "Behavior": 0,
                        "Name": "DK1",
                        "Value": "1 584,73",
                        "GroupHeader": "",
                        "DisplayNegativeValueInBlue": false,
                        "CombinedName": "DK1",
                        "DateTimeForData": "0001-01-01T00:00:00",
                        "DisplayName": "1 584,73_False",
                        "DisplayNameOrDominatingDirection": "1 584,73",
                        "IsOfficial": false,
                        "UseDashDisplayStyle": false
                    },
                    {
                        "Index": 1,
                        "Scale": 2,
                        "SecondaryValue": null,
                        "IsDominatingDirection": false,
                        "IsValid": true,
                        "IsAdditionalData": false,
                        "Behavior": 0,
                        "Name": "DK2",
                        "Value": "1 588,97",
                        "GroupHeader": "",
                        "DisplayNegativeValueInBlue": false,
                        "CombinedName": "DK2",
                        "DateTimeForData": "0001-01-01T00:00:00",
                        "DisplayName": "1 588,97_False",
                        "DisplayNameOrDominatingDirection": "1 588,97",
                        "IsOfficial": false,
                        "UseDashDisplayStyle": false
                    }
                ],
                "Name": "05&nbsp;-&nbsp;06",
                "StartTime": "2022-12-04T05:00:00",
                "EndTime": "2022-12-04T06:00:00",
                "DateTimeForData": "0001-01-01T00:00:00",
                "DayNumber": 0,
                "StartTimeDate": "0001-01-01T00:00:00",
                "IsExtraRow": false,
                "IsNtcRow": false,
                "EmptyValue": "",
                "Parent": null
            },
            {
                "Columns": [
                    {
                        "Index": 0,
                        "Scale": 2,
                        "SecondaryValue": null,
                        "IsDominatingDirection": false,
                        "IsValid": true,
                        "IsAdditionalData": false,
                        "Behavior": 0,
                        "Name": "DK1",
                        "Value": "1 575,51",
                        "GroupHeader": "",
                        "DisplayNegativeValueInBlue": false,
                        "CombinedName": "DK1",
                        "DateTimeForData": "0001-01-01T00:00:00",
                        "DisplayName": "1 575,51_False",
                        "DisplayNameOrDominatingDirection": "1 575,51",
                        "IsOfficial": false,
                        "UseDashDisplayStyle": false
                    },
                    {
                        "Index": 1,
                        "Scale": 2,
                        "SecondaryValue": null,
                        "IsDominatingDirection": false,
                        "IsValid": true,
                        "IsAdditionalData": false,
                        "Behavior": 0,
                        "Name": "DK2",
                        "Value": "1 575,96",
                        "GroupHeader": "",
                        "DisplayNegativeValueInBlue": false,
                        "CombinedName": "DK2",
                        "DateTimeForData": "0001-01-01T00:00:00",
                        "DisplayName": "1 575,96_False",
                        "DisplayNameOrDominatingDirection": "1 575,96",
                        "IsOfficial": false,
                        "UseDashDisplayStyle": false
                    }
                ],
                "Name": "06&nbsp;-&nbsp;07",
                "StartTime": "2022-12-04T06:00:00",
                "EndTime": "2022-12-04T07:00:00",
                "DateTimeForData": "0001-01-01T00:00:00",
                "DayNumber": 0,
                "StartTimeDate": "0001-01-01T00:00:00",
                "IsExtraRow": false,
                "IsNtcRow": false,
                "EmptyValue": "",
                "Parent": null
            },
            {
                "Columns": [
                    {
                        "Index": 0,
                        "Scale": 2,
                        "SecondaryValue": null,
                        "IsDominatingDirection": false,
                        "IsValid": true,
                        "IsAdditionalData": false,
                        "Behavior": 0,
                        "Name": "DK1",
                        "Value": "1 627,72",
                        "GroupHeader": "",
                        "DisplayNegativeValueInBlue": false,
                        "CombinedName": "DK1",
                        "DateTimeForData": "0001-01-01T00:00:00",
                        "DisplayName": "1 627,72_False",
                        "DisplayNameOrDominatingDirection": "1 627,72",
                        "IsOfficial": false,
                        "UseDashDisplayStyle": false
                    },
                    {
                        "Index": 1,
                        "Scale": 2,
                        "SecondaryValue": null,
                        "IsDominatingDirection": false,
                        "IsValid": true,
                        "IsAdditionalData": false,
                        "Behavior": 0,
                        "Name": "DK2",
                        "Value": "1 663,79",
                        "GroupHeader": "",
                        "DisplayNegativeValueInBlue": false,
                        "CombinedName": "DK2",
                        "DateTimeForData": "0001-01-01T00:00:00",
                        "DisplayName": "1 663,79_False",
                        "DisplayNameOrDominatingDirection": "1 663,79",
                        "IsOfficial": false,
                        "UseDashDisplayStyle": false
                    }
                ],
                "Name": "07&nbsp;-&nbsp;08",
                "StartTime": "2022-12-04T07:00:00",
                "EndTime": "2022-12-04T08:00:00",
                "DateTimeForData": "0001-01-01T00:00:00",
                "DayNumber": 0,
                "StartTimeDate": "0001-01-01T00:00:00",
                "IsExtraRow": false,
                "IsNtcRow": false,
                "EmptyValue": "",
                "Parent": null
            },
            {
                "Columns": [
                    {
                        "Index": 0,
                        "Scale": 2,
                        "SecondaryValue": null,
                        "IsDominatingDirection": false,
                        "IsValid": true,
                        "IsAdditionalData": false,
                        "Behavior": 0,
                        "Name": "DK1",
                        "Value": "1 898,73",
                        "GroupHeader": "",
                        "DisplayNegativeValueInBlue": false,
                        "CombinedName": "DK1",
                        "DateTimeForData": "0001-01-01T00:00:00",
                        "DisplayName": "1 898,73_False",
                        "DisplayNameOrDominatingDirection": "1 898,73",
                        "IsOfficial": false,
                        "UseDashDisplayStyle": false
                    },
                    {
                        "Index": 1,
                        "Scale": 2,
                        "SecondaryValue": null,
                        "IsDominatingDirection": false,
                        "IsValid": true,
                        "IsAdditionalData": false,
                        "Behavior": 0,
                        "Name": "DK2",
                        "Value": "1 898,73",
                        "GroupHeader": "",
                        "DisplayNegativeValueInBlue": false,
                        "CombinedName": "DK2",
                        "DateTimeForData": "0001-01-01T00:00:00",
                        "DisplayName": "1 898,73_False",
                        "DisplayNameOrDominatingDirection": "1 898,73",
                        "IsOfficial": false,
                        "UseDashDisplayStyle": false
                    }
                ],
                "Name": "08&nbsp;-&nbsp;09",
                "StartTime": "2022-12-04T08:00:00",
                "EndTime": "2022-12-04T09:00:00",
                "DateTimeForData": "0001-01-01T00:00:00",
                "DayNumber": 0,
                "StartTimeDate": "0001-01-01T00:00:00",
                "IsExtraRow": false,
                "IsNtcRow": false,
                "EmptyValue": "",
                "Parent": null
            },
            {
                "Columns": [
                    {
                        "Index": 0,
                        "Scale": 2,
                        "SecondaryValue": null,
                        "IsDominatingDirection": false,
                        "IsValid": true,
                        "IsAdditionalData": false,
                        "Behavior": 0,
                        "Name": "DK1",
                        "Value": "2 096,49",
                        "GroupHeader": "",
                        "DisplayNegativeValueInBlue": false,
                        "CombinedName": "DK1",
                        "DateTimeForData": "0001-01-01T00:00:00",
                        "DisplayName": "2 096,49_False",
                        "DisplayNameOrDominatingDirection": "2 096,49",
                        "IsOfficial": false,
                        "UseDashDisplayStyle": false
                    },
                    {
                        "Index": 1,
                        "Scale": 2,
                        "SecondaryValue": null,
                        "IsDominatingDirection": false,
                        "IsValid": true,
                        "IsAdditionalData": false,
                        "Behavior": 0,
                        "Name": "DK2",
                        "Value": "2 096,49",
                        "GroupHeader": "",
                        "DisplayNegativeValueInBlue": false,
                        "CombinedName": "DK2",
                        "DateTimeForData": "0001-01-01T00:00:00",
                        "DisplayName": "2 096,49_False",
                        "DisplayNameOrDominatingDirection": "2 096,49",
                        "IsOfficial": false,
                        "UseDashDisplayStyle": false
                    }
                ],
                "Name": "09&nbsp;-&nbsp;10",
                "StartTime": "2022-12-04T09:00:00",
                "EndTime": "2022-12-04T10:00:00",
                "DateTimeForData": "0001-01-01T00:00:00",
                "DayNumber": 0,
                "StartTimeDate": "0001-01-01T00:00:00",
                "IsExtraRow": false,
                "IsNtcRow": false,
                "EmptyValue": "",
                "Parent": null
            },
            {
                "Columns": [
                    {
                        "Index": 0,
                        "Scale": 2,
                        "SecondaryValue": null,
                        "IsDominatingDirection": false,
                        "IsValid": true,
                        "IsAdditionalData": false,
                        "Behavior": 0,
                        "Name": "DK1",
                        "Value": "2 182,98",
                        "GroupHeader": "",
                        "DisplayNegativeValueInBlue": false,
                        "CombinedName": "DK1",
                        "DateTimeForData": "0001-01-01T00:00:00",
                        "DisplayName": "2 182,98_False",
                        "DisplayNameOrDominatingDirection": "2 182,98",
                        "IsOfficial": false,
                        "UseDashDisplayStyle": false
                    },
                    {
                        "Index": 1,
                        "Scale": 2,
                        "SecondaryValue": null,
                        "IsDominatingDirection": false,
                        "IsValid": true,
                        "IsAdditionalData": false,
                        "Behavior": 0,
                        "Name": "DK2",
                        "Value": "2 182,98",
                        "GroupHeader": "",
                        "DisplayNegativeValueInBlue": false,
                        "CombinedName": "DK2",
                        "DateTimeForData": "0001-01-01T00:00:00",
                        "DisplayName": "2 182,98_False",
                        "DisplayNameOrDominatingDirection": "2 182,98",
                        "IsOfficial": false,
                        "UseDashDisplayStyle": false
                    }
                ],
                "Name": "10&nbsp;-&nbsp;11",
                "StartTime": "2022-12-04T10:00:00",
                "EndTime": "2022-12-04T11:00:00",
                "DateTimeForData": "0001-01-01T00:00:00",
                "DayNumber": 0,
                "StartTimeDate": "0001-01-01T00:00:00",
                "IsExtraRow": false,
                "IsNtcRow": false,
                "EmptyValue": "",
                "Parent": null
            },
            {
                "Columns": [
                    {
                        "Index": 0,
                        "Scale": 2,
                        "SecondaryValue": null,
                        "IsDominatingDirection": false,
                        "IsValid": true,
                        "IsAdditionalData": false,
                        "Behavior": 0,
                        "Name": "DK1",
                        "Value": "2 225,30",
                        "GroupHeader": "",
                        "DisplayNegativeValueInBlue": false,
                        "CombinedName": "DK1",
                        "DateTimeForData": "0001-01-01T00:00:00",
                        "DisplayName": "2 225,30_False",
                        "DisplayNameOrDominatingDirection": "2 225,30",
                        "IsOfficial": false,
                        "UseDashDisplayStyle": false
                    },
                    {
                        "Index": 1,
                        "Scale": 2,
                        "SecondaryValue": null,
                        "IsDominatingDirection": false,
                        "IsValid": true,
                        "IsAdditionalData": false,
                        "Behavior": 0,
                        "Name": "DK2",
                        "Value": "2 225,30",
                        "GroupHeader": "",
                        "DisplayNegativeValueInBlue": false,
                        "CombinedName": "DK2",
                        "DateTimeForData": "0001-01-01T00:00:00",
                        "DisplayName": "2 225,30_False",
                        "DisplayNameOrDominatingDirection": "2 225,30",
                        "IsOfficial": false,
                        "UseDashDisplayStyle": false
                    }
                ],
                "Name": "11&nbsp;-&nbsp;12",
                "StartTime": "2022-12-04T11:00:00",
                "EndTime": "2022-12-04T12:00:00",
                "DateTimeForData": "0001-01-01T00:00:00",
                "DayNumber": 0,
                "StartTimeDate": "0001-01-01T00:00:00",
                "IsExtraRow": false,
                "IsNtcRow": false,
                "EmptyValue": "",
                "Parent": null
            },
            {
                "Columns": [
                    {
                        "Index": 0,
                        "Scale": 2,
                        "SecondaryValue": null,
                        "IsDominatingDirection": false,
                        "IsValid": true,
                        "IsAdditionalData": false,
                        "Behavior": 0,
                        "Name": "DK1",
                        "Value": "2 212,81",
                        "GroupHeader": "",
                        "DisplayNegativeValueInBlue": false,
                        "CombinedName": "DK1",
                        "DateTimeForData": "0001-01-01T00:00:00",
                        "DisplayName": "2 212,81_False",
                        "DisplayNameOrDominatingDirection": "2 212,81",
                        "IsOfficial": false,
                        "UseDashDisplayStyle": false
                    },
                    {
                        "Index": 1,
                        "Scale": 2,
                        "SecondaryValue": null,
                        "IsDominatingDirection": false,
                        "IsValid": true,
                        "IsAdditionalData": false,
                        "Behavior": 0,
                        "Name": "DK2",
                        "Value": "2 212,81",
                        "GroupHeader": "",
                        "DisplayNegativeValueInBlue": false,
                        "CombinedName": "DK2",
                        "DateTimeForData": "0001-01-01T00:00:00",
                        "DisplayName": "2 212,81_False",
                        "DisplayNameOrDominatingDirection": "2 212,81",
                        "IsOfficial": false,
                        "UseDashDisplayStyle": false
                    }
                ],
                "Name": "12&nbsp;-&nbsp;13",
                "StartTime": "2022-12-04T12:00:00",
                "EndTime": "2022-12-04T13:00:00",
                "DateTimeForData": "0001-01-01T00:00:00",
                "DayNumber": 0,
                "StartTimeDate": "0001-01-01T00:00:00",
                "IsExtraRow": false,
                "IsNtcRow": false,
                "EmptyValue": "",
                "Parent": null
            },
            {
                "Columns": [
                    {
                        "Index": 0,
                        "Scale": 2,
                        "SecondaryValue": null,
                        "IsDominatingDirection": false,
                        "IsValid": true,
                        "IsAdditionalData": false,
                        "Behavior": 0,
                        "Name": "DK1",
                        "Value": "2 188,71",
                        "GroupHeader": "",
                        "DisplayNegativeValueInBlue": false,
                        "CombinedName": "DK1",
                        "DateTimeForData": "0001-01-01T00:00:00",
                        "DisplayName": "2 188,71_False",
                        "DisplayNameOrDominatingDirection": "2 188,71",
                        "IsOfficial": false,
                        "UseDashDisplayStyle": false
                    },
                    {
                        "Index": 1,
                        "Scale": 2,
                        "SecondaryValue": null,
                        "IsDominatingDirection": false,
                        "IsValid": true,
                        "IsAdditionalData": false,
                        "Behavior": 0,
                        "Name": "DK2",
                        "Value": "2 188,71",
                        "GroupHeader": "",
                        "DisplayNegativeValueInBlue": false,
                        "CombinedName": "DK2",
                        "DateTimeForData": "0001-01-01T00:00:00",
                        "DisplayName": "2 188,71_False",
                        "DisplayNameOrDominatingDirection": "2 188,71",
                        "IsOfficial": false,
                        "UseDashDisplayStyle": false
                    }
                ],
                "Name": "13&nbsp;-&nbsp;14",
                "StartTime": "2022-12-04T13:00:00",
                "EndTime": "2022-12-04T14:00:00",
                "DateTimeForData": "0001-01-01T00:00:00",
                "DayNumber": 0,
                "StartTimeDate": "0001-01-01T00:00:00",
                "IsExtraRow": false,
                "IsNtcRow": false,
                "EmptyValue": "",
                "Parent": null
            },
            {
                "Columns": [
                    {
                        "Index": 0,
                        "Scale": 2,
                        "SecondaryValue": null,
                        "IsDominatingDirection": false,
                        "IsValid": true,
                        "IsAdditionalData": false,
                        "Behavior": 0,
                        "Name": "DK1",
                        "Value": "2 205,74",
                        "GroupHeader": "",
                        "DisplayNegativeValueInBlue": false,
                        "CombinedName": "DK1",
                        "DateTimeForData": "0001-01-01T00:00:00",
                        "DisplayName": "2 205,74_False",
                        "DisplayNameOrDominatingDirection": "2 205,74",
                        "IsOfficial": false,
                        "UseDashDisplayStyle": false
                    },
                    {
                        "Index": 1,
                        "Scale": 2,
                        "SecondaryValue": null,
                        "IsDominatingDirection": false,
                        "IsValid": true,
                        "IsAdditionalData": false,
                        "Behavior": 0,
                        "Name": "DK2",
                        "Value": "2 205,74",
                        "GroupHeader": "",
                        "DisplayNegativeValueInBlue": false,
                        "CombinedName": "DK2",
                        "DateTimeForData": "0001-01-01T00:00:00",
                        "DisplayName": "2 205,74_False",
                        "DisplayNameOrDominatingDirection": "2 205,74",
                        "IsOfficial": false,
                        "UseDashDisplayStyle": false
                    }
                ],
                "Name": "14&nbsp;-&nbsp;15",
                "StartTime": "2022-12-04T14:00:00",
                "EndTime": "2022-12-04T15:00:00",
                "DateTimeForData": "0001-01-01T00:00:00",
                "DayNumber": 0,
                "StartTimeDate": "0001-01-01T00:00:00",
                "IsExtraRow": false,
                "IsNtcRow": false,
                "EmptyValue": "",
                "Parent": null
            },
            {
                "Columns": [
                    {
                        "Index": 0,
                        "Scale": 2,
                        "SecondaryValue": null,
                        "IsDominatingDirection": false,
                        "IsValid": true,
                        "IsAdditionalData": false,
                        "Behavior": 0,
                        "Name": "DK1",
                        "Value": "2 219,13",
                        "GroupHeader": "",
                        "DisplayNegativeValueInBlue": false,
                        "CombinedName": "DK1",
                        "DateTimeForData": "0001-01-01T00:00:00",
                        "DisplayName": "2 219,13_False",
                        "DisplayNameOrDominatingDirection": "2 219,13",
                        "IsOfficial": false,
                        "UseDashDisplayStyle": false
                    },
                    {
                        "Index": 1,
                        "Scale": 2,
                        "SecondaryValue": null,
                        "IsDominatingDirection": false,
                        "IsValid": true,
                        "IsAdditionalData": false,
                        "Behavior": 0,
                        "Name": "DK2",
                        "Value": "2 219,13",
                        "GroupHeader": "",
                        "DisplayNegativeValueInBlue": false,
                        "CombinedName": "DK2",
                        "DateTimeForData": "0001-01-01T00:00:00",
                        "DisplayName": "2 219,13_False",
                        "DisplayNameOrDominatingDirection": "2 219,13",
                        "IsOfficial": false,
                        "UseDashDisplayStyle": false
                    }
                ],
                "Name": "15&nbsp;-&nbsp;16",
                "StartTime": "2022-12-04T15:00:00",
                "EndTime": "2022-12-04T16:00:00",
                "DateTimeForData": "0001-01-01T00:00:00",
                "DayNumber": 0,
                "StartTimeDate": "0001-01-01T00:00:00",
                "IsExtraRow": false,
                "IsNtcRow": false,
                "EmptyValue": "",
                "Parent": null
            },
            {
                "Columns": [
                    {
                        "Index": 0,
                        "Scale": 2,
                        "SecondaryValue": null,
                        "IsDominatingDirection": false,
                        "IsValid": true,
                        "IsAdditionalData": false,
                        "Behavior": 0,
                        "Name": "DK1",
                        "Value": "2 341,47",
                        "GroupHeader": "",
                        "DisplayNegativeValueInBlue": false,
                        "CombinedName": "DK1",
                        "DateTimeForData": "0001-01-01T00:00:00",
                        "DisplayName": "2 341,47_False",
                        "DisplayNameOrDominatingDirection": "2 341,47",
                        "IsOfficial": false,
                        "UseDashDisplayStyle": false
                    },
                    {
                        "Index": 1,
                        "Scale": 2,
                        "SecondaryValue": null,
                        "IsDominatingDirection": false,
                        "IsValid": true,
                        "IsAdditionalData": false,
                        "Behavior": 0,
                        "Name": "DK2",
                        "Value": "2 341,47",
                        "GroupHeader": "",
                        "DisplayNegativeValueInBlue": false,
                        "CombinedName": "DK2",
                        "DateTimeForData": "0001-01-01T00:00:00",
                        "DisplayName": "2 341,47_False",
                        "DisplayNameOrDominatingDirection": "2 341,47",
                        "IsOfficial": false,
                        "UseDashDisplayStyle": false
                    }
                ],
                "Name": "16&nbsp;-&nbsp;17",
                "StartTime": "2022-12-04T16:00:00",
                "EndTime": "2022-12-04T17:00:00",
                "DateTimeForData": "0001-01-01T00:00:00",
                "DayNumber": 0,
                "StartTimeDate": "0001-01-01T00:00:00",
                "IsExtraRow": false,
                "IsNtcRow": false,
                "EmptyValue": "",
                "Parent": null
            },
            {
                "Columns": [
                    {
                        "Index": 0,
                        "Scale": 2,
                        "SecondaryValue": null,
                        "IsDominatingDirection": false,
                        "IsValid": true,
                        "IsAdditionalData": false,
                        "Behavior": 0,
                        "Name": "DK1",
                        "Value": "2 503,75",
                        "GroupHeader": "",
                        "DisplayNegativeValueInBlue": false,
                        "CombinedName": "DK1",
                        "DateTimeForData": "0001-01-01T00:00:00",
                        "DisplayName": "2 503,75_False",
                        "DisplayNameOrDominatingDirection": "2 503,75",
                        "IsOfficial": false,
                        "UseDashDisplayStyle": false
                    },
                    {
                        "Index": 1,
                        "Scale": 2,
                        "SecondaryValue": null,
                        "IsDominatingDirection": false,
                        "IsValid": true,
                        "IsAdditionalData": false,
                        "Behavior": 0,
                        "Name": "DK2",
                        "Value": "2 503,75",
                        "GroupHeader": "",
                        "DisplayNegativeValueInBlue": false,
                        "CombinedName": "DK2",
                        "DateTimeForData": "0001-01-01T00:00:00",
                        "DisplayName": "2 503,75_False",
                        "DisplayNameOrDominatingDirection": "2 503,75",
                        "IsOfficial": false,
                        "UseDashDisplayStyle": false
                    }
                ],
                "Name": "17&nbsp;-&nbsp;18",
                "StartTime": "2022-12-04T17:00:00",
                "EndTime": "2022-12-04T18:00:00",
                "DateTimeForData": "0001-01-01T00:00:00",
                "DayNumber": 0,
                "StartTimeDate": "0001-01-01T00:00:00",
                "IsExtraRow": false,
                "IsNtcRow": false,
                "EmptyValue": "",
                "Parent": null
            },
            {
                "Columns": [
                    {
                        "Index": 0,
                        "Scale": 2,
                        "SecondaryValue": null,
                        "IsDominatingDirection": false,
                        "IsValid": true,
                        "IsAdditionalData": false,
                        "Behavior": 0,
                        "Name": "DK1",
                        "Value": "2 197,04",
                        "GroupHeader": "",
                        "DisplayNegativeValueInBlue": false,
                        "CombinedName": "DK1",
                        "DateTimeForData": "0001-01-01T00:00:00",
                        "DisplayName": "2 197,04_False",
                        "DisplayNameOrDominatingDirection": "2 197,04",
                        "IsOfficial": false,
                        "UseDashDisplayStyle": false
                    },
                    {
                        "Index": 1,
                        "Scale": 2,
                        "SecondaryValue": null,
                        "IsDominatingDirection": false,
                        "IsValid": true,
                        "IsAdditionalData": false,
                        "Behavior": 0,
                        "Name": "DK2",
                        "Value": "2 197,04",
                        "GroupHeader": "",
                        "DisplayNegativeValueInBlue": false,
                        "CombinedName": "DK2",
                        "DateTimeForData": "0001-01-01T00:00:00",
                        "DisplayName": "2 197,04_False",
                        "DisplayNameOrDominatingDirection": "2 197,04",
                        "IsOfficial": false,
                        "UseDashDisplayStyle": false
                    }
                ],
                "Name": "18&nbsp;-&nbsp;19",
                "StartTime": "2022-12-04T18:00:00",
                "EndTime": "2022-12-04T19:00:00",
                "DateTimeForData": "0001-01-01T00:00:00",
                "DayNumber": 0,
                "StartTimeDate": "0001-01-01T00:00:00",
                "IsExtraRow": false,
                "IsNtcRow": false,
                "EmptyValue": "",
                "Parent": null
            },
            {
                "Columns": [
                    {
                        "Index": 0,
                        "Scale": 2,
                        "SecondaryValue": null,
                        "IsDominatingDirection": false,
                        "IsValid": true,
                        "IsAdditionalData": false,
                        "Behavior": 0,
                        "Name": "DK1",
                        "Value": "2 176,44",
                        "GroupHeader": "",
                        "DisplayNegativeValueInBlue": false,
                        "CombinedName": "DK1",
                        "DateTimeForData": "0001-01-01T00:00:00",
                        "DisplayName": "2 176,44_False",
                        "DisplayNameOrDominatingDirection": "2 176,44",
                        "IsOfficial": false,
                        "UseDashDisplayStyle": false
                    },
                    {
                        "Index": 1,
                        "Scale": 2,
                        "SecondaryValue": null,
                        "IsDominatingDirection": false,
                        "IsValid": true,
                        "IsAdditionalData": false,
                        "Behavior": 0,
                        "Name": "DK2",
                        "Value": "2 176,44",
                        "GroupHeader": "",
                        "DisplayNegativeValueInBlue": false,
                        "CombinedName": "DK2",
                        "DateTimeForData": "0001-01-01T00:00:00",
                        "DisplayName": "2 176,44_False",
                        "DisplayNameOrDominatingDirection": "2 176,44",
                        "IsOfficial": false,
                        "UseDashDisplayStyle": false
                    }
                ],
                "Name": "19&nbsp;-&nbsp;20",
                "StartTime": "2022-12-04T19:00:00",
                "EndTime": "2022-12-04T20:00:00",
                "DateTimeForData": "0001-01-01T00:00:00",
                "DayNumber": 0,
                "StartTimeDate": "0001-01-01T00:00:00",
                "IsExtraRow": false,
                "IsNtcRow": false,
                "EmptyValue": "",
                "Parent": null
            },
            {
                "Columns": [
                    {
                        "Index": 0,
                        "Scale": 2,
                        "SecondaryValue": null,
                        "IsDominatingDirection": false,
                        "IsValid": true,
                        "IsAdditionalData": false,
                        "Behavior": 0,
                        "Name": "DK1",
                        "Value": "1 941,65",
                        "GroupHeader": "",
                        "DisplayNegativeValueInBlue": false,
                        "CombinedName": "DK1",
                        "DateTimeForData": "0001-01-01T00:00:00",
                        "DisplayName": "1 941,65_False",
                        "DisplayNameOrDominatingDirection": "1 941,65",
                        "IsOfficial": false,
                        "UseDashDisplayStyle": false
                    },
                    {
                        "Index": 1,
                        "Scale": 2,
                        "SecondaryValue": null,
                        "IsDominatingDirection": false,
                        "IsValid": true,
                        "IsAdditionalData": false,
                        "Behavior": 0,
                        "Name": "DK2",
                        "Value": "1 941,65",
                        "GroupHeader": "",
                        "DisplayNegativeValueInBlue": false,
                        "CombinedName": "DK2",
                        "DateTimeForData": "0001-01-01T00:00:00",
                        "DisplayName": "1 941,65_False",
                        "DisplayNameOrDominatingDirection": "1 941,65",
                        "IsOfficial": false,
                        "UseDashDisplayStyle": false
                    }
                ],
                "Name": "20&nbsp;-&nbsp;21",
                "StartTime": "2022-12-04T20:00:00",
                "EndTime": "2022-12-04T21:00:00",
                "DateTimeForData": "0001-01-01T00:00:00",
                "DayNumber": 0,
                "StartTimeDate": "0001-01-01T00:00:00",
                "IsExtraRow": false,
                "IsNtcRow": false,
                "EmptyValue": "",
                "Parent": null
            },
            {
                "Columns": [
                    {
                        "Index": 0,
                        "Scale": 2,
                        "SecondaryValue": null,
                        "IsDominatingDirection": false,
                        "IsValid": true,
                        "IsAdditionalData": false,
                        "Behavior": 0,
                        "Name": "DK1",
                        "Value": "2 007,76",
                        "GroupHeader": "",
                        "DisplayNegativeValueInBlue": false,
                        "CombinedName": "DK1",
                        "DateTimeForData": "0001-01-01T00:00:00",
                        "DisplayName": "2 007,76_False",
                        "DisplayNameOrDominatingDirection": "2 007,76",
                        "IsOfficial": false,
                        "UseDashDisplayStyle": false
                    },
                    {
                        "Index": 1,
                        "Scale": 2,
                        "SecondaryValue": null,
                        "IsDominatingDirection": false,
                        "IsValid": true,
                        "IsAdditionalData": false,
                        "Behavior": 0,
                        "Name": "DK2",
                        "Value": "2 007,76",
                        "GroupHeader": "",
                        "DisplayNegativeValueInBlue": false,
                        "CombinedName": "DK2",
                        "DateTimeForData": "0001-01-01T00:00:00",
                        "DisplayName": "2 007,76_False",
                        "DisplayNameOrDominatingDirection": "2 007,76",
                        "IsOfficial": false,
                        "UseDashDisplayStyle": false
                    }
                ],
                "Name": "21&nbsp;-&nbsp;22",
                "StartTime": "2022-12-04T21:00:00",
                "EndTime": "2022-12-04T22:00:00",
                "DateTimeForData": "0001-01-01T00:00:00",
                "DayNumber": 0,
                "StartTimeDate": "0001-01-01T00:00:00",
                "IsExtraRow": false,
                "IsNtcRow": false,
                "EmptyValue": "",
                "Parent": null
            },
            {
                "Columns": [
                    {
                        "Index": 0,
                        "Scale": 2,
                        "SecondaryValue": null,
                        "IsDominatingDirection": false,
                        "IsValid": true,
                        "IsAdditionalData": false,
                        "Behavior": 0,
                        "Name": "DK1",
                        "Value": "1 916,21",
                        "GroupHeader": "",
                        "DisplayNegativeValueInBlue": false,
                        "CombinedName": "DK1",
                        "DateTimeForData": "0001-01-01T00:00:00",
                        "DisplayName": "1 916,21_False",
                        "DisplayNameOrDominatingDirection": "1 916,21",
                        "IsOfficial": false,
                        "UseDashDisplayStyle": false
                    },
                    {
                        "Index": 1,
                        "Scale": 2,
                        "SecondaryValue": null,
                        "IsDominatingDirection": false,
                        "IsValid": true,
                        "IsAdditionalData": false,
                        "Behavior": 0,
                        "Name": "DK2",
                        "Value": "1 916,21",
                        "GroupHeader": "",
                        "DisplayNegativeValueInBlue": false,
                        "CombinedName": "DK2",
                        "DateTimeForData": "0001-01-01T00:00:00",
                        "DisplayName": "1 916,21_False",
                        "DisplayNameOrDominatingDirection": "1 916,21",
                        "IsOfficial": false,
                        "UseDashDisplayStyle": false
                    }
                ],
                "Name": "22&nbsp;-&nbsp;23",
                "StartTime": "2022-12-04T22:00:00",
                "EndTime": "2022-12-04T23:00:00",
                "DateTimeForData": "0001-01-01T00:00:00",
                "DayNumber": 0,
                "StartTimeDate": "0001-01-01T00:00:00",
                "IsExtraRow": false,
                "IsNtcRow": false,
                "EmptyValue": "",
                "Parent": null
            },
            {
                "Columns": [
                    {
                        "Index": 0,
                        "Scale": 2,
                        "SecondaryValue": null,
                        "IsDominatingDirection": false,
                        "IsValid": true,
                        "IsAdditionalData": false,
                        "Behavior": 0,
                        "Name": "DK1",
                        "Value": "1 786,06",
                        "GroupHeader": "",
                        "DisplayNegativeValueInBlue": false,
                        "CombinedName": "DK1",
                        "DateTimeForData": "0001-01-01T00:00:00",
                        "DisplayName": "1 786,06_False",
                        "DisplayNameOrDominatingDirection": "1 786,06",
                        "IsOfficial": false,
                        "UseDashDisplayStyle": false
                    },
                    {
                        "Index": 1,
                        "Scale": 2,
                        "SecondaryValue": null,
                        "IsDominatingDirection": false,
                        "IsValid": true,
                        "IsAdditionalData": false,
                        "Behavior": 0,
                        "Name": "DK2",
                        "Value": "1 786,06",
                        "GroupHeader": "",
                        "DisplayNegativeValueInBlue": false,
                        "CombinedName": "DK2",
                        "DateTimeForData": "0001-01-01T00:00:00",
                        "DisplayName": "1 786,06_False",
                        "DisplayNameOrDominatingDirection": "1 786,06",
                        "IsOfficial": false,
                        "UseDashDisplayStyle": false
                    }
                ],
                "Name": "23&nbsp;-&nbsp;00",
                "StartTime": "2022-12-04T23:00:00",
                "EndTime": "2022-12-05T00:00:00",
                "DateTimeForData": "0001-01-01T00:00:00",
                "DayNumber": 0,
                "StartTimeDate": "0001-01-01T00:00:00",
                "IsExtraRow": false,
                "IsNtcRow": false,
                "EmptyValue": "",
                "Parent": null
            },
            {
                "Columns": [
                    {
                        "Index": 0,
                        "Scale": 0,
                        "SecondaryValue": null,
                        "IsDominatingDirection": false,
                        "IsValid": false,
                        "IsAdditionalData": false,
                        "Behavior": 0,
                        "Name": "DK1",
                        "Value": "1 550,82",
                        "GroupHeader": null,
                        "DisplayNegativeValueInBlue": false,
                        "CombinedName": "DK1",
                        "DateTimeForData": "0001-01-01T00:00:00",
                        "DisplayName": "1 550,82_True",
                        "DisplayNameOrDominatingDirection": "1 550,82",
                        "IsOfficial": true,
                        "UseDashDisplayStyle": false
                    },
                    {
                        "Index": 0,
                        "Scale": 0,
                        "SecondaryValue": null,
                        "IsDominatingDirection": false,
                        "IsValid": false,
                        "IsAdditionalData": false,
                        "Behavior": 0,
                        "Name": "DK2",
                        "Value": "1 557,44",
                        "GroupHeader": null,
                        "DisplayNegativeValueInBlue": false,
                        "CombinedName": "DK2",
                        "DateTimeForData": "0001-01-01T00:00:00",
                        "DisplayName": "1 557,44_True",
                        "DisplayNameOrDominatingDirection": "1 557,44",
                        "IsOfficial": true,
                        "UseDashDisplayStyle": false
                    }
                ],
                "Name": "Min",
                "StartTime": "2022-12-04T00:00:00",
                "EndTime": "2022-12-05T00:00:00",
                "DateTimeForData": "0001-01-01T00:00:00",
                "DayNumber": 0,
                "StartTimeDate": "0001-01-01T00:00:00",
                "IsExtraRow": true,
                "IsNtcRow": false,
                "EmptyValue": "",
                "Parent": null
            },
            {
                "Columns": [
                    {
                        "Index": 0,
                        "Scale": 0,
                        "SecondaryValue": null,
                        "IsDominatingDirection": false,
                        "IsValid": false,
                        "IsAdditionalData": false,
                        "Behavior": 0,
                        "Name": "DK1",
                        "Value": "2 503,75",
                        "GroupHeader": null,
                        "DisplayNegativeValueInBlue": false,
                        "CombinedName": "DK1",
                        "DateTimeForData": "0001-01-01T00:00:00",
                        "DisplayName": "2 503,75_True",
                        "DisplayNameOrDominatingDirection": "2 503,75",
                        "IsOfficial": true,
                        "UseDashDisplayStyle": false
                    },
                    {
                        "Index": 0,
                        "Scale": 0,
                        "SecondaryValue": null,
                        "IsDominatingDirection": false,
                        "IsValid": false,
                        "IsAdditionalData": false,
                        "Behavior": 0,
                        "Name": "DK2",
                        "Value": "2 503,75",
                        "GroupHeader": null,
                        "DisplayNegativeValueInBlue": false,
                        "CombinedName": "DK2",
                        "DateTimeForData": "0001-01-01T00:00:00",
                        "DisplayName": "2 503,75_True",
                        "DisplayNameOrDominatingDirection": "2 503,75",
                        "IsOfficial": true,
                        "UseDashDisplayStyle": false
                    }
                ],
                "Name": "Max",
                "StartTime": "2022-12-04T00:00:00",
                "EndTime": "2022-12-05T00:00:00",
                "DateTimeForData": "0001-01-01T00:00:00",
                "DayNumber": 0,
                "StartTimeDate": "0001-01-01T00:00:00",
                "IsExtraRow": true,
                "IsNtcRow": false,
                "EmptyValue": "",
                "Parent": null
            },
            {
                "Columns": [
                    {
                        "Index": 0,
                        "Scale": 2,
                        "SecondaryValue": null,
                        "IsDominatingDirection": false,
                        "IsValid": true,
                        "IsAdditionalData": false,
                        "Behavior": 0,
                        "Name": "DK1",
                        "Value": "1 960,95",
                        "GroupHeader": null,
                        "DisplayNegativeValueInBlue": false,
                        "CombinedName": "DK1",
                        "DateTimeForData": "0001-01-01T00:00:00",
                        "DisplayName": "1 960,95_False",
                        "DisplayNameOrDominatingDirection": "1 960,95",
                        "IsOfficial": false,
                        "UseDashDisplayStyle": false
                    },
                    {
                        "Index": 1,
                        "Scale": 2,
                        "SecondaryValue": null,
                        "IsDominatingDirection": false,
                        "IsValid": true,
                        "IsAdditionalData": false,
                        "Behavior": 0,
                        "Name": "DK2",
                        "Value": "1 963,51",
                        "GroupHeader": null,
                        "DisplayNegativeValueInBlue": false,
                        "CombinedName": "DK2",
                        "DateTimeForData": "0001-01-01T00:00:00",
                        "DisplayName": "1 963,51_False",
                        "DisplayNameOrDominatingDirection": "1 963,51",
                        "IsOfficial": false,
                        "UseDashDisplayStyle": false
                    }
                ],
                "Name": "Average",
                "StartTime": "2022-12-04T00:00:00",
                "EndTime": "2022-12-05T00:00:00",
                "DateTimeForData": "0001-01-01T00:00:00",
                "DayNumber": 0,
                "StartTimeDate": "0001-01-01T00:00:00",
                "IsExtraRow": true,
                "IsNtcRow": false,
                "EmptyValue": "",
                "Parent": null
            },
            {
                "Columns": [
                    {
                        "Index": 0,
                        "Scale": 2,
                        "SecondaryValue": null,
                        "IsDominatingDirection": false,
                        "IsValid": true,
                        "IsAdditionalData": false,
                        "Behavior": 0,
                        "Name": "DK1",
                        "Value": "2 204,05",
                        "GroupHeader": null,
                        "DisplayNegativeValueInBlue": false,
                        "CombinedName": "DK1",
                        "DateTimeForData": "0001-01-01T00:00:00",
                        "DisplayName": "2 204,05_False",
                        "DisplayNameOrDominatingDirection": "2 204,05",
                        "IsOfficial": false,
                        "UseDashDisplayStyle": false
                    },
                    {
                        "Index": 1,
                        "Scale": 2,
                        "SecondaryValue": null,
                        "IsDominatingDirection": false,
                        "IsValid": true,
                        "IsAdditionalData": false,
                        "Behavior": 0,
                        "Name": "DK2",
                        "Value": "2 204,05",
                        "GroupHeader": null,
                        "DisplayNegativeValueInBlue": false,
                        "CombinedName": "DK2",
                        "DateTimeForData": "0001-01-01T00:00:00",
                        "DisplayName": "2 204,05_False",
                        "DisplayNameOrDominatingDirection": "2 204,05",
                        "IsOfficial": false,
                        "UseDashDisplayStyle": false
                    }
                ],
                "Name": "Peak",
                "StartTime": "2022-12-04T00:00:00",
                "EndTime": "2022-12-05T00:00:00",
                "DateTimeForData": "0001-01-01T00:00:00",
                "DayNumber": 0,
                "StartTimeDate": "0001-01-01T00:00:00",
                "IsExtraRow": true,
                "IsNtcRow": false,
                "EmptyValue": "",
                "Parent": null
            },
            {
                "Columns": [
                    {
                        "Index": 0,
                        "Scale": 2,
                        "SecondaryValue": null,
                        "IsDominatingDirection": false,
                        "IsValid": true,
                        "IsAdditionalData": false,
                        "Behavior": 0,
                        "Name": "DK1",
                        "Value": "1 620,32",
                        "GroupHeader": null,
                        "DisplayNegativeValueInBlue": false,
                        "CombinedName": "DK1",
                        "DateTimeForData": "0001-01-01T00:00:00",
                        "DisplayName": "1 620,32_False",
                        "DisplayNameOrDominatingDirection": "1 620,32",
                        "IsOfficial": false,
                        "UseDashDisplayStyle": false
                    },
                    {
                        "Index": 1,
                        "Scale": 2,
                        "SecondaryValue": null,
                        "IsDominatingDirection": false,
                        "IsValid": true,
                        "IsAdditionalData": false,
                        "Behavior": 0,
                        "Name": "DK2",
                        "Value": "1 627,99",
                        "GroupHeader": null,
                        "DisplayNegativeValueInBlue": false,
                        "CombinedName": "DK2",
                        "DateTimeForData": "0001-01-01T00:00:00",
                        "DisplayName": "1 627,99_False",
                        "DisplayNameOrDominatingDirection": "1 627,99",
                        "IsOfficial": false,
                        "UseDashDisplayStyle": false
                    }
                ],
                "Name": "Off-peak 1",
                "StartTime": "2022-12-04T00:00:00",
                "EndTime": "2022-12-05T00:00:00",
                "DateTimeForData": "0001-01-01T00:00:00",
                "DayNumber": 0,
                "StartTimeDate": "0001-01-01T00:00:00",
                "IsExtraRow": true,
                "IsNtcRow": false,
                "EmptyValue": "",
                "Parent": null
            },
            {
                "Columns": [
                    {
                        "Index": 0,
                        "Scale": 2,
                        "SecondaryValue": null,
                        "IsDominatingDirection": false,
                        "IsValid": true,
                        "IsAdditionalData": false,
                        "Behavior": 0,
                        "Name": "DK1",
                        "Value": "1 912,92",
                        "GroupHeader": null,
                        "DisplayNegativeValueInBlue": false,
                        "CombinedName": "DK1",
                        "DateTimeForData": "0001-01-01T00:00:00",
                        "DisplayName": "1 912,92_False",
                        "DisplayNameOrDominatingDirection": "1 912,92",
                        "IsOfficial": false,
                        "UseDashDisplayStyle": false
                    },
                    {
                        "Index": 1,
                        "Scale": 2,
                        "SecondaryValue": null,
                        "IsDominatingDirection": false,
                        "IsValid": true,
                        "IsAdditionalData": false,
                        "Behavior": 0,
                        "Name": "DK2",
                        "Value": "1 912,92",
                        "GroupHeader": null,
                        "DisplayNegativeValueInBlue": false,
                        "CombinedName": "DK2",
                        "DateTimeForData": "0001-01-01T00:00:00",
                        "DisplayName": "1 912,92_False",
                        "DisplayNameOrDominatingDirection": "1 912,92",
                        "IsOfficial": false,
                        "UseDashDisplayStyle": false
                    }
                ],
                "Name": "Off-peak 2",
                "StartTime": "2022-12-04T00:00:00",
                "EndTime": "2022-12-05T00:00:00",
                "DateTimeForData": "0001-01-01T00:00:00",
                "DayNumber": 0,
                "StartTimeDate": "0001-01-01T00:00:00",
                "IsExtraRow": true,
                "IsNtcRow": false,
                "EmptyValue": "",
                "Parent": null
            }
        ],
        "IsDivided": true,
        "SectionNames": [
            "05.12.2022"
        ],
        "EntityIDs": [
            "1f9326c0-d951-11df-a60f-920b69901433",
            "10fbf820-da33-11df-905a-e3d6c5079852",
            "30781a40-d951-11df-a60f-920b69901433",
            "11767f50-da33-11df-905a-e3d6c5079852",
            "830c32b0-d950-11df-a60f-920b69901433",
            "fb4ad690-da32-11df-905a-e3d6c5079852",
            "920d23f0-d950-11df-a60f-920b69901433",
            "fb9f8640-da32-11df-905a-e3d6c5079852",
            "db8b2a50-5ebf-11e0-be4c-f1c6caf7663c",
            "651fe960-9721-11e0-b750-e6e36421fc2f",
            "d5c4e4d0-5ebf-11e0-be4c-f1c6caf7663c",
            "a56c7ba0-9721-11e0-b750-e6e36421fc2f",
            "9ca21fb0-5ebf-11e0-be4c-f1c6caf7663c",
            "0f0e6a00-9722-11e0-b750-e6e36421fc2f",
            "96b36aa0-5ebf-11e0-be4c-f1c6caf7663c",
            "0ee0f160-9722-11e0-b750-e6e36421fc2f",
            "38a11480-5ebf-11e0-be4c-f1c6caf7663c",
            "3292ae60-9726-11e0-b750-e6e36421fc2f",
            "2cb09790-5ebf-11e0-be4c-f1c6caf7663c",
            "327a6b70-9726-11e0-b750-e6e36421fc2f"
        ],
        "DataStartdate": "2022-12-04T00:00:00",
        "DataEnddate": "2022-12-05T00:00:00",
        "MinDateForTimeScale": "2021-01-01T00:00:00",
        "AreaChanges": [],
        "Units": [
            "DKK/MWh"
        ],
        "LatestResultDate": "2022-12-04T00:00:00",
        "ContainsPreliminaryValues": true,
        "ContainsExchangeRates": true,
        "ExchangeRateOfficial": null,
        "ExchangeRatePreliminary": "7,4373",
        "ExchangeUnit": "",
        "DateUpdated": "2022-12-03T12:47:38.181",
        "CombinedHeadersEnabled": false,
        "DataType": 0,
        "TimeZoneInformation": 0
    },
    "cacheKey": "B3F78C97C42810FEBC3F9067A1E4CF4D",
    "conf": {
        "Id": "a0c6818f-14d1-4537-83cb-65d639e5f69c",
        "Name": null,
        "Published": "0001-01-01T00:00:00",
        "ShowGraph": true,
        "ResolutionPeriod": {
            "Id": "485c4400-d2ca-47be-900b-8e09cbf51035",
            "Resolution": 0,
            "Unit": 0,
            "PeriodNumber": 1
        },
        "ResolutionPeriodY": {
            "Id": "11b4a15e-f070-4a5f-87d2-71135ffb14e3",
            "Resolution": 0,
            "Unit": 0,
            "PeriodNumber": 8
        },
        "Entities": [
            {
                "ProductType": {
                    "Id": "3b7ea0de-9756-4a37-8291-b8d6152c61ce",
                    "Attributes": [
                        {
                            "Id": "12f13371-9c9a-4072-b953-cb4098a2c19b",
                            "Name": "Area",
                            "Role": "",
                            "HasRoles": false,
                            "Values": [
                                "AT",
                                "BE",
                                "DE",
                                "DK1",
                                "DK2",
                                "EE",
                                "ELE",
                                "FI",
                                "FR",
                                "FRE",
                                "GER",
                                "KT",
                                "LT",
                                "LV",
                                "NL",
                                "NO1",
                                "NO2",
                                "NO3",
                                "NO4",
                                "NO5",
                                "SE",
                                "SE1",
                                "SE2",
                                "SE3",
                                "SE4"
                            ]
                        },
                        {
                            "Id": "f7bf901b-0128-4e58-b41b-0e01f4fa824d",
                            "Name": "Currency",
                            "Role": "",
                            "HasRoles": false,
                            "Values": [
                                "EUR",
                                "DKK",
                                "NOK",
                                "SEK"
                            ]
                        },
                        {
                            "Id": "5ce2212f-b6b4-4876-b476-1f643b1a2be6",
                            "Name": "Official",
                            "Role": "",
                            "HasRoles": false,
                            "Values": [
                                "false",
                                "true"
                            ]
                        },
                        {
                            "Id": "0ed51831-85ca-4ddb-aa63-0f50647be453",
                            "Name": "Unit",
                            "Role": "",
                            "HasRoles": false,
                            "Values": [
                                "EUR/MWh",
                                "DKK/MWh",
                                "NOK/MWh",
                                "SEK/MWh"
                            ]
                        }
                    ],
                    "Name": "ELSP_PRI_ARE_H",
                    "DisplayName": "The ElSpot area prices.                                                                                                                               "
                },
                "SecondaryProductType": {
                    "Id": "46e42ea7-0a95-4c8c-bceb-7cc3f3259a2f",
                    "Attributes": null,
                    "Name": "NA",
                    "DisplayName": "-- Not applicable --"
                },
                "SecondaryProductBehavior": 0,
                "Id": "d97f7501-b0b9-fa4d-a771-a272ddfb815d",
                "Name": "DK1",
                "GroupHeader": "",
                "DataUpdated": "0001-01-01T00:00:00",
                "Attributes": [
                    {
                        "Id": "12f13371-9c9a-4072-b953-cb4098a2c19b",
                        "Name": "Area",
                        "HasRoles": false,
                        "Role": "",
                        "Value": "DK1"
                    },
                    {
                        "Id": "f7bf901b-0128-4e58-b41b-0e01f4fa824d",
                        "Name": "Currency",
                        "HasRoles": false,
                        "Role": "",
                        "Value": "DKK"
                    },
                    {
                        "Id": "5ce2212f-b6b4-4876-b476-1f643b1a2be6",
                        "Name": "Official",
                        "HasRoles": false,
                        "Role": "",
                        "Value": "false"
                    },
                    {
                        "Id": "0ed51831-85ca-4ddb-aa63-0f50647be453",
                        "Name": "Unit",
                        "HasRoles": false,
                        "Role": "",
                        "Value": "DKK/MWh"
                    }
                ],
                "Drillable": true,
                "DateRanges": [],
                "Index": 0,
                "IndexForColumn": 0,
                "MinMaxDisabled": false,
                "DisableNumberGroupSeparator": 0,
                "TimeserieID": null,
                "SecondaryTimeserieID": "00000000-0000-0000-0000-000000000000",
                "HasPreliminary": false,
                "TimeseriePreliminaryID": null,
                "Scale": 0,
                "SecondaryScale": 0,
                "DataType": 0,
                "SecondaryDataType": 0,
                "LastUpdate": "0001-01-01T00:00:00",
                "Unit": "DKK/MWh",
                "IsDominatingDirection": false,
                "DisplayAsSeparatedColumn": false,
                "EnableInChart": false,
                "BlueNegativeValues": false
            },
            {
                "ProductType": {
                    "Id": "3b7ea0de-9756-4a37-8291-b8d6152c61ce",
                    "Attributes": [
                        {
                            "Id": "12f13371-9c9a-4072-b953-cb4098a2c19b",
                            "Name": "Area",
                            "Role": "",
                            "HasRoles": false,
                            "Values": [
                                "AT",
                                "BE",
                                "DE",
                                "DK1",
                                "DK2",
                                "EE",
                                "ELE",
                                "FI",
                                "FR",
                                "FRE",
                                "GER",
                                "KT",
                                "LT",
                                "LV",
                                "NL",
                                "NO1",
                                "NO2",
                                "NO3",
                                "NO4",
                                "NO5",
                                "SE",
                                "SE1",
                                "SE2",
                                "SE3",
                                "SE4"
                            ]
                        },
                        {
                            "Id": "f7bf901b-0128-4e58-b41b-0e01f4fa824d",
                            "Name": "Currency",
                            "Role": "",
                            "HasRoles": false,
                            "Values": [
                                "EUR",
                                "DKK",
                                "NOK",
                                "SEK"
                            ]
                        },
                        {
                            "Id": "5ce2212f-b6b4-4876-b476-1f643b1a2be6",
                            "Name": "Official",
                            "Role": "",
                            "HasRoles": false,
                            "Values": [
                                "false",
                                "true"
                            ]
                        },
                        {
                            "Id": "0ed51831-85ca-4ddb-aa63-0f50647be453",
                            "Name": "Unit",
                            "Role": "",
                            "HasRoles": false,
                            "Values": [
                                "EUR/MWh",
                                "DKK/MWh",
                                "NOK/MWh",
                                "SEK/MWh"
                            ]
                        }
                    ],
                    "Name": "ELSP_PRI_ARE_H",
                    "DisplayName": "The ElSpot area prices.                                                                                                                               "
                },
                "SecondaryProductType": {
                    "Id": "46e42ea7-0a95-4c8c-bceb-7cc3f3259a2f",
                    "Attributes": null,
                    "Name": "NA",
                    "DisplayName": "-- Not applicable --"
                },
                "SecondaryProductBehavior": 0,
                "Id": "d97f7501-b0b9-fa4d-a771-a272ddfb815d",
                "Name": "DK2",
                "GroupHeader": "",
                "DataUpdated": "0001-01-01T00:00:00",
                "Attributes": [
                    {
                        "Id": "12f13371-9c9a-4072-b953-cb4098a2c19b",
                        "Name": "Area",
                        "HasRoles": false,
                        "Role": "",
                        "Value": "DK2"
                    },
                    {
                        "Id": "f7bf901b-0128-4e58-b41b-0e01f4fa824d",
                        "Name": "Currency",
                        "HasRoles": false,
                        "Role": "",
                        "Value": "DKK"
                    },
                    {
                        "Id": "5ce2212f-b6b4-4876-b476-1f643b1a2be6",
                        "Name": "Official",
                        "HasRoles": false,
                        "Role": "",
                        "Value": "false"
                    },
                    {
                        "Id": "0ed51831-85ca-4ddb-aa63-0f50647be453",
                        "Name": "Unit",
                        "HasRoles": false,
                        "Role": "",
                        "Value": "DKK/MWh"
                    }
                ],
                "Drillable": true,
                "DateRanges": [],
                "Index": 1,
                "IndexForColumn": 1,
                "MinMaxDisabled": false,
                "DisableNumberGroupSeparator": 0,
                "TimeserieID": null,
                "SecondaryTimeserieID": "00000000-0000-0000-0000-000000000000",
                "HasPreliminary": false,
                "TimeseriePreliminaryID": null,
                "Scale": 0,
                "SecondaryScale": 0,
                "DataType": 0,
                "SecondaryDataType": 0,
                "LastUpdate": "0001-01-01T00:00:00",
                "Unit": "DKK/MWh",
                "IsDominatingDirection": false,
                "DisplayAsSeparatedColumn": false,
                "EnableInChart": false,
                "BlueNegativeValues": false
            }
        ],
        "TableType": 0,
        "ExtraRows": [
            {
                "Id": "72f337c0-c2cb-4737-844c-a12ad52641dc",
                "Header": "Average",
                "ColumnProducts": [
                    "ELSP_PRI_ARE_DA",
                    "ELSP_PRI_ARE_DA"
                ]
            },
            {
                "Id": "b222ec26-9588-4313-b798-cacd0dfee586",
                "Header": "Peak",
                "ColumnProducts": [
                    "ELSP_PRI_ARE_PEAK_DA",
                    "ELSP_PRI_ARE_PEAK_DA"
                ]
            },
            {
                "Id": "1749fc8c-0334-42f7-ae10-001cdb0b1c0b",
                "Header": "Off-peak 1",
                "ColumnProducts": [
                    "ELSP_PRI_ARE_OFFPEAK1_DA",
                    "ELSP_PRI_ARE_OFFPEAK1_DA"
                ]
            },
            {
                "Id": "b2946d98-d7f1-4f96-aa30-b72c95286e0f",
                "Header": "Off-peak 2",
                "ColumnProducts": [
                    "ELSP_PRI_ARE_OFFPEAK2_DA",
                    "ELSP_PRI_ARE_OFFPEAK2_DA"
                ]
            }
        ],
        "Filters": [
            {
                "Id": "e2195d1d-b0a5-47fb-88fe-3a72644df692",
                "AttributeName": "Currency",
                "Values": [
                    "EUR",
                    "DKK",
                    "NOK",
                    "SEK"
                ],
                "DefaultValue": "EUR"
            }
        ],
        "IsDrillDownEnabled": true,
        "DrillDownMode": 1,
        "IsMinValueEnabled": true,
        "IsMaxValueEnabled": true,
        "ValidYearsBack": 1,
        "TimeScaleUnit": "Year",
        "IsNtcEnabled": false,
        "NtcProductType": {
            "Id": "b8ef0fc3-58ac-46c7-be6f-284b5abc99ec",
            "Attributes": null,
            "Name": "NA",
            "DisplayName": "-- Not applicable --"
        },
        "NtcHeader": "",
        "ShowTimelineGraph": 1,
        "ExchangeMode": 0,
        "IsPivotTable": 0,
        "IsCombinedHeadersEnabled": 0,
        "NtcFormat": 0,
        "DisplayHourAlsoInUKTime": false
    },
    "header": {
        "title": "Day-ahead prices",
        "description": "",
        "questionMarkInfo": "<p><strong>Day-head&nbsp;prices</strong> represent the result of Nord Pools day-ahead implicit auction market.&nbsp;</p>\n<p>&nbsp;</p>\n<p>&nbsp;</p>\n<p>&nbsp;</p>\n<p>Peak = 09:00 to 20:00</p>\n<p>Off peak 1 = 01:00 to 08:00</p>\n<p>Off peak 2 = 21:00 to 24:00</p>\n<p>Average = arithmetic average</p>",
        "hideDownloadButton": "True"
    },
    "endDate": null,
    "currency": "DKK",
    "pageId": 41
}